{
	"carName": "mclaren_720s_gt3_evo",
	"basicSetup":
	{
		"tyres":
		{
			"tyreCompound": 0,
			"tyrePressure": [ 51, 47, 49, 47 ]
		},
		"alignment":
		{
			"camber": [ 0, 0, 0, 0 ],
			"toe": [ 18, 18, 13, 13 ],
			"staticCamber": [ -4.6868491172790527, -4.6895604133605957, -4.6727771759033203, -4.6741352081298828 ],
			"toeOutLinear": [ 0.0021382772829383612, 0.0021382691338658333, 7.8745957580395043e-05, 7.874972652643919e-05 ],
			"casterLF": 46,
			"casterRF": 46,
			"steerRatio": 0
		},
		"electronics":
		{
			"tC1": 2,
			"tC2": 0,
			"abs": 2,
			"eCUMap": 0,
			"fuelMix": 0,
			"telemetryLaps": 99
		},
		"strategy":
		{
			"fuel": 44,
			"nPitStops": 0,
			"tyreSet": 3,
			"frontBrakePadCompound": 0,
			"rearBrakePadCompound": 0,
			"pitStrategy": [
				{
					"fuelToAdd": 0,
					"tyres":
					{
						"tyreCompound": 0,
						"tyrePressure": [ 54, 51, 47, 45 ]
					},
					"tyreSet": 2,
					"frontBrakePadCompound": 1,
					"rearBrakePadCompound": 1
				},
				{
					"fuelToAdd": 0,
					"tyres":
					{
						"tyreCompound": 0,
						"tyrePressure": [ 52, 48, 50, 48 ]
					},
					"tyreSet": 2,
					"frontBrakePadCompound": 0,
					"rearBrakePadCompound": 0
				},
				{
					"fuelToAdd": 0,
					"tyres":
					{
						"tyreCompound": 0,
						"tyrePressure": [ 52, 48, 50, 48 ]
					},
					"tyreSet": 2,
					"frontBrakePadCompound": 0,
					"rearBrakePadCompound": 0
				},
				{
					"fuelToAdd": 0,
					"tyres":
					{
						"tyreCompound": 0,
						"tyrePressure": [ 52, 48, 50, 48 ]
					},
					"tyreSet": 2,
					"frontBrakePadCompound": 0,
					"rearBrakePadCompound": 0
				},
				{
					"fuelToAdd": 0,
					"tyres":
					{
						"tyreCompound": 0,
						"tyrePressure": [ 52, 48, 50, 48 ]
					},
					"tyreSet": 2,
					"frontBrakePadCompound": 0,
					"rearBrakePadCompound": 0
				},
				{
					"fuelToAdd": 0,
					"tyres":
					{
						"tyreCompound": 0,
						"tyrePressure": [ 52, 48, 50, 48 ]
					},
					"tyreSet": 2,
					"frontBrakePadCompound": 0,
					"rearBrakePadCompound": 0
				},
				{
					"fuelToAdd": 0,
					"tyres":
					{
						"tyreCompound": 0,
						"tyrePressure": [ 52, 48, 50, 48 ]
					},
					"tyreSet": 2,
					"frontBrakePadCompound": 0,
					"rearBrakePadCompound": 0
				},
				{
					"fuelToAdd": 0,
					"tyres":
					{
						"tyreCompound": 0,
						"tyrePressure": [ 52, 48, 50, 48 ]
					},
					"tyreSet": 2,
					"frontBrakePadCompound": 0,
					"rearBrakePadCompound": 0
				},
				{
					"fuelToAdd": 0,
					"tyres":
					{
						"tyreCompound": 0,
						"tyrePressure": [ 52, 48, 50, 48 ]
					},
					"tyreSet": 2,
					"frontBrakePadCompound": 0,
					"rearBrakePadCompound": 0
				},
				{
					"fuelToAdd": 0,
					"tyres":
					{
						"tyreCompound": 0,
						"tyrePressure": [ 52, 48, 50, 48 ]
					},
					"tyreSet": 2,
					"frontBrakePadCompound": 0,
					"rearBrakePadCompound": 0
				},
				{
					"fuelToAdd": 0,
					"tyres":
					{
						"tyreCompound": 0,
						"tyrePressure": [ 52, 48, 50, 48 ]
					},
					"tyreSet": 2,
					"frontBrakePadCompound": 0,
					"rearBrakePadCompound": 0
				},
				{
					"fuelToAdd": 0,
					"tyres":
					{
						"tyreCompound": 0,
						"tyrePressure": [ 52, 48, 50, 48 ]
					},
					"tyreSet": 2,
					"frontBrakePadCompound": 0,
					"rearBrakePadCompound": 0
				},
				{
					"fuelToAdd": 0,
					"tyres":
					{
						"tyreCompound": 0,
						"tyrePressure": [ 52, 48, 50, 48 ]
					},
					"tyreSet": 2,
					"frontBrakePadCompound": 0,
					"rearBrakePadCompound": 0
				},
				{
					"fuelToAdd": 0,
					"tyres":
					{
						"tyreCompound": 0,
						"tyrePressure": [ 52, 48, 50, 48 ]
					},
					"tyreSet": 2,
					"frontBrakePadCompound": 0,
					"rearBrakePadCompound": 0
				},
				{
					"fuelToAdd": 0,
					"tyres":
					{
						"tyreCompound": 0,
						"tyrePressure": [ 52, 48, 50, 48 ]
					},
					"tyreSet": 2,
					"frontBrakePadCompound": 0,
					"rearBrakePadCompound": 0
				},
				{
					"fuelToAdd": 0,
					"tyres":
					{
						"tyreCompound": 0,
						"tyrePressure": [ 52, 48, 50, 48 ]
					},
					"tyreSet": 2,
					"frontBrakePadCompound": 0,
					"rearBrakePadCompound": 0
				},
				{
					"fuelToAdd": 0,
					"tyres":
					{
						"tyreCompound": 0,
						"tyrePressure": [ 52, 48, 50, 48 ]
					},
					"tyreSet": 2,
					"frontBrakePadCompound": 0,
					"rearBrakePadCompound": 0
				},
				{
					"fuelToAdd": 0,
					"tyres":
					{
						"tyreCompound": 0,
						"tyrePressure": [ 52, 48, 50, 48 ]
					},
					"tyreSet": 2,
					"frontBrakePadCompound": 0,
					"rearBrakePadCompound": 0
				},
				{
					"fuelToAdd": 0,
					"tyres":
					{
						"tyreCompound": 0,
						"tyrePressure": [ 52, 48, 50, 48 ]
					},
					"tyreSet": 2,
					"frontBrakePadCompound": 0,
					"rearBrakePadCompound": 0
				},
				{
					"fuelToAdd": 0,
					"tyres":
					{
						"tyreCompound": 0,
						"tyrePressure": [ 52, 48, 50, 48 ]
					},
					"tyreSet": 2,
					"frontBrakePadCompound": 0,
					"rearBrakePadCompound": 0
				},
				{
					"fuelToAdd": 0,
					"tyres":
					{
						"tyreCompound": 0,
						"tyrePressure": [ 52, 48, 50, 48 ]
					},
					"tyreSet": 2,
					"frontBrakePadCompound": 0,
					"rearBrakePadCompound": 0
				},
				{
					"fuelToAdd": 0,
					"tyres":
					{
						"tyreCompound": 0,
						"tyrePressure": [ 52, 48, 50, 48 ]
					},
					"tyreSet": 2,
					"frontBrakePadCompound": 0,
					"rearBrakePadCompound": 0
				},
				{
					"fuelToAdd": 0,
					"tyres":
					{
						"tyreCompound": 0,
						"tyrePressure": [ 52, 48, 50, 48 ]
					},
					"tyreSet": 2,
					"frontBrakePadCompound": 0,
					"rearBrakePadCompound": 0
				},
				{
					"fuelToAdd": 0,
					"tyres":
					{
						"tyreCompound": 0,
						"tyrePressure": [ 52, 48, 50, 48 ]
					},
					"tyreSet": 2,
					"frontBrakePadCompound": 0,
					"rearBrakePadCompound": 0
				},
				{
					"fuelToAdd": 0,
					"tyres":
					{
						"tyreCompound": 0,
						"tyrePressure": [ 52, 48, 50, 48 ]
					},
					"tyreSet": 2,
					"frontBrakePadCompound": 0,
					"rearBrakePadCompound": 0
				},
				{
					"fuelToAdd": 0,
					"tyres":
					{
						"tyreCompound": 0,
						"tyrePressure": [ 52, 48, 50, 48 ]
					},
					"tyreSet": 2,
					"frontBrakePadCompound": 0,
					"rearBrakePadCompound": 0
				},
				{
					"fuelToAdd": 0,
					"tyres":
					{
						"tyreCompound": 0,
						"tyrePressure": [ 52, 48, 50, 48 ]
					},
					"tyreSet": 2,
					"frontBrakePadCompound": 0,
					"rearBrakePadCompound": 0
				},
				{
					"fuelToAdd": 0,
					"tyres":
					{
						"tyreCompound": 0,
						"tyrePressure": [ 52, 48, 50, 48 ]
					},
					"tyreSet": 2,
					"frontBrakePadCompound": 0,
					"rearBrakePadCompound": 0
				},
				{
					"fuelToAdd": 0,
					"tyres":
					{
						"tyreCompound": 0,
						"tyrePressure": [ 52, 48, 50, 48 ]
					},
					"tyreSet": 2,
					"frontBrakePadCompound": 0,
					"rearBrakePadCompound": 0
				},
				{
					"fuelToAdd": 0,
					"tyres":
					{
						"tyreCompound": 0,
						"tyrePressure": [ 52, 48, 50, 48 ]
					},
					"tyreSet": 2,
					"frontBrakePadCompound": 0,
					"rearBrakePadCompound": 0
				}
			],
			"fuelPerLap": 3.2999999523162842
		}
	},
	"advancedSetup":
	{
		"mechanicalBalance":
		{
			"aRBFront": 11,
			"aRBRear": 8,
			"wheelRate": [ 3, 3, 0, 0 ],
			"bumpStopRateUp": [ 0, 0, 0, 0 ],
			"bumpStopRateDn": [ 0, 0, 10, 10 ],
			"bumpStopWindow": [ 40, 40, 27, 27 ],
			"brakeTorque": 20,
			"brakeBias": 13
		},
		"dampers":
		{
			"bumpSlow": [ 0, 0, 0, 0 ],
			"bumpFast": [ 0, 0, 0, 0 ],
			"reboundSlow": [ 40, 40, 40, 40 ],
			"reboundFast": [ 39, 39, 39, 39 ]
		},
		"aeroBalance":
		{
			"rideHeight": [ 0, 6, 5, 18 ],
			"rodLength": [ 52.307365417480469, 52.307365417480469, 45.309432983398438, 45.309432983398438 ],
			"splitter": 0,
			"rearWing": 2,
			"brakeDuct": [ 2, 2 ]
		},
		"drivetrain":
		{
			"preload": 10
		}
	},
	"trackBopType": 27
}